SDD/__init__.py
SDD/data/__init__.py
SDD/debug/__init__.py
SDD/outputs/__init__.py
SDD/utils/Detector.py
SDD/utils/Models.py
SDD/utils/Run.py
SDD/utils/VideoRead.py
SDD/utils/View_Transformer.py
SDD/utils/__init__.py
SDDect-0.1.0.dist-info/LICENSE
SDDect-0.1.0.dist-info/METADATA
SDDect-0.1.0.dist-info/WHEEL
SDDect-0.1.0.dist-info/top_level.txt
SDDect-0.1.0.dist-info/zip-safe
SDDect-0.1.0.dist-info/RECORD
